unoserver/__init__.py
unoserver/client.py
unoserver/comparer.py
unoserver/converter.py
unoserver/server.py
unoserver_appx-1.0.1.dist-info/LICENSE
unoserver_appx-1.0.1.dist-info/METADATA
unoserver_appx-1.0.1.dist-info/WHEEL
unoserver_appx-1.0.1.dist-info/entry_points.txt
unoserver_appx-1.0.1.dist-info/top_level.txt
unoserver_appx-1.0.1.dist-info/RECORD
