Metadata-Version: 2.1
Name: unoserver_appx
Version: 1.0.1
Summary: A server for file conversions with Libre Office
Author-email: Lennart Regebro <regebro@gmail.com>
License: MIT
Project-URL: Homepage, https://github.com/unoconv/unoserver
Keywords: libreoffice,conversion,documents,uno,unoconv
Classifier: Development Status :: 5 - Production/Stable
Classifier: Topic :: Office/Business
Classifier: Operating System :: POSIX :: Linux
Classifier: Programming Language :: Python :: 3
Classifier: Programming Language :: Python :: 3 :: Only
Classifier: Programming Language :: Python :: 3.8
Classifier: Programming Language :: Python :: 3.9
Classifier: Programming Language :: Python :: 3.10
Classifier: Programming Language :: Python :: 3.11
Classifier: Programming Language :: Python :: 3.12
Classifier: License :: OSI Approved :: MIT License
Requires-Python: >=3.8
License-File: LICENSE
Provides-Extra: devenv
Requires-Dist: pytest ; extra == 'devenv'
Requires-Dist: pytest-cov ; extra == 'devenv'
Requires-Dist: black ; extra == 'devenv'
Requires-Dist: flake8 ; extra == 'devenv'
Requires-Dist: pyroma ; extra == 'devenv'
Requires-Dist: check-manifest ; extra == 'devenv'
Requires-Dist: zest.releaser ; extra == 'devenv'
